stackuchin/__init__.py
stackuchin/create.py
stackuchin/delete.py
stackuchin/start_pipeline.py
stackuchin/update.py
stackuchin/utilities.py
stackuchin-1.6.0.dist-info/LICENSE
stackuchin-1.6.0.dist-info/METADATA
stackuchin-1.6.0.dist-info/WHEEL
stackuchin-1.6.0.dist-info/entry_points.txt
stackuchin-1.6.0.dist-info/top_level.txt
stackuchin-1.6.0.dist-info/RECORD
