Metadata-Version: 2.1
Name: stackuchin
Version: 1.6.0
Summary: CLI for Stackuchin - Automatically create, update and delete AWS CloudFormation stacks in multiple AWS accounts and regions at the same time
Home-page: https://github.com/Rungutan/stackuchin
Author: Rungutan
Author-email: support@rungutan.com
License: UNKNOWN
Download-URL: https://github.com/Rungutan/stackuchin/archive/1.6.0.tar.gz
Project-URL: Bug Reports, https://github.com/Rungutan/stackuchin/issues
Project-URL: Source, https://github.com/Rungutan/stackuchin/
Keywords: stackuchin stackuchin-cli stackuchin_cli cli aws cloudformation stacks deployment integrationcotinuous continuos devops tools
Platform: UNKNOWN
Classifier: Development Status :: 5 - Production/Stable
Classifier: Intended Audience :: Developers
Classifier: Intended Audience :: Information Technology
Classifier: Intended Audience :: System Administrators
Classifier: Topic :: Software Development :: Testing
Classifier: Topic :: Software Development :: Quality Assurance
Classifier: Topic :: Software Development :: Testing :: Acceptance
Classifier: Topic :: Software Development :: Testing :: BDD
Classifier: Topic :: Software Development :: Testing :: Mocking
Classifier: Topic :: Software Development :: Testing :: Traffic Generation
Classifier: Topic :: Software Development :: Testing :: Unit
Classifier: License :: OSI Approved :: MIT License
Classifier: Programming Language :: Python :: 3
Classifier: Programming Language :: Python :: 3.5
Classifier: Programming Language :: Python :: 3.6
Classifier: Programming Language :: Python :: 3.7
Classifier: Programming Language :: Python :: 3.8
Classifier: Programming Language :: Python :: 3 :: Only
Requires-Python: >=3.5, <4
Requires-Dist: simplejson
Requires-Dist: boto3
Requires-Dist: botocore
Requires-Dist: pyyaml
Requires-Dist: requests
Provides-Extra: test
Requires-Dist: coverage ; extra == 'test'
